{
  "duration": 5,
  "sensors": [
    {
      "accelerometer": {
        "x": 0.3975045,
        "y": 4.0916715,
        "z": 8.263644
      },
      "ambientLight": 155.1,
      "gyroscope": {
        "x": 0.11395255,
        "y": 0.11009537,
        "z": -1.7453292E-4
      },
      "proximity": 5.0,
      "timestamp": 1763978753927
    },
    {
      "accelerometer": {
        "x": 0.3975045,
        "y": 4.0916715,
        "z": 8.263644
      },
      "ambientLight": 194.3,
      "gyroscope": {
        "x": -0.06808529,
        "y": -1.5869406,
        "z": 0.59388316
      },
      "proximity": 5.0,
      "timestamp": 1763978754031
    },
    {
      "accelerometer": {
        "x": 2.6495864,
        "y": 4.0595894,
        "z": 5.872239
      },
      "ambientLight": 194.3,
      "gyroscope": {
        "x": -0.06808529,
        "y": -1.5869406,
        "z": 0.59388316
      },
      "proximity": 5.0,
      "timestamp": 1763978754134
    },
    {
      "accelerometer": {
        "x": 2.6495864,
        "y": 4.0595894,
        "z": 5.872239
      },
      "ambientLight": 194.3,
      "gyroscope": {
        "x": -0.21820106,
        "y": -1.5805527,
        "z": 0.94521797
      },
      "proximity": 5.0,
      "timestamp": 1763978754234
    },
    {
      "accelerometer": {
        "x": 3.1889138,
        "y": -0.9767098,
        "z": 7.952226
      },
      "ambientLight": 227.90001,
      "gyroscope": {
        "x": -0.21820106,
        "y": -1.5805527,
        "z": 0.94521797
      },
      "proximity": 5.0,
      "timestamp": 1763978754335
    },
    {
      "accelerometer": {
        "x": 3.1889138,
        "y": -0.9767098,
        "z": 7.952226
      },
      "ambientLight": 227.90001,
      "gyroscope": {
        "x": -0.51523864,
        "y": -1.4442774,
        "z": 2.198312
      },
      "proximity": 5.0,
      "timestamp": 1763978754435
    },
    {
      "accelerometer": {
        "x": 11.101128,
        "y": -0.8388325,
        "z": 6.080305
      },
      "ambientLight": 227.90001,
      "gyroscope": {
        "x": -0.51523864,
        "y": -1.4442774,
        "z": 2.198312
      },
      "proximity": 5.0,
      "timestamp": 1763978754535
    },
    {
      "accelerometer": {
        "x": 11.101128,
        "y": -0.8388325,
        "z": 6.080305
      },
      "ambientLight": 227.90001,
      "gyroscope": {
        "x": -0.69729394,
        "y": -0.47225118,
        "z": 0.62901664
      },
      "proximity": 5.0,
      "timestamp": 1763978754636
    },
    {
      "accelerometer": {
        "x": 12.075128,
        "y": -2.4222617,
        "z": 3.5092485
      },
      "ambientLight": 212.1,
      "gyroscope": {
        "x": -0.69729394,
        "y": -0.47225118,
        "z": 0.62901664
      },
      "proximity": 5.0,
      "timestamp": 1763978754737
    },
    {
      "accelerometer": {
        "x": 12.075128,
        "y": -2.4222617,
        "z": 3.5092485
      },
      "ambientLight": 212.1,
      "gyroscope": {
        "x": -0.28314477,
        "y": 0.5966408,
        "z": 0.3032335
      },
      "proximity": 5.0,
      "timestamp": 1763978754837
    },
    {
      "accelerometer": {
        "x": 11.558009,
        "y": -3.1407807,
        "z": 1.8837099
      },
      "ambientLight": 212.1,
      "gyroscope": {
        "x": -0.28314477,
        "y": 0.5966408,
        "z": 0.3032335
      },
      "proximity": 5.0,
      "timestamp": 1763978754960
    },
    {
      "accelerometer": {
        "x": 11.558009,
        "y": -3.1407807,
        "z": 1.8837099
      },
      "ambientLight": 79.700005,
      "gyroscope": {
        "x": 0.73890257,
        "y": -0.39346704,
        "z": 0.26597074
      },
      "proximity": 5.0,
      "timestamp": 1763978755060
    },
    {
      "accelerometer": {
        "x": 12.630209,
        "y": 0.8959581,
        "z": -4.1209574
      },
      "ambientLight": 79.700005,
      "gyroscope": {
        "x": 0.73890257,
        "y": -0.39346704,
        "z": 0.26597074
      },
      "proximity": 5.0,
      "timestamp": 1763978755160
    },
    {
      "accelerometer": {
        "x": 12.630209,
        "y": 0.8959581,
        "z": -4.1209574
      },
      "ambientLight": 79.700005,
      "gyroscope": {
        "x": -1.8620219,
        "y": 3.6064088,
        "z": 0.1712168
      },
      "proximity": 5.0,
      "timestamp": 1763978755261
    },
    {
      "accelerometer": {
        "x": 6.0004535,
        "y": -5.262149,
        "z": 8.899458
      },
      "ambientLight": 59.2,
      "gyroscope": {
        "x": -1.8620219,
        "y": 3.6064088,
        "z": 0.1712168
      },
      "proximity": 5.0,
      "timestamp": 1763978755361
    },
    {
      "accelerometer": {
        "x": 6.0004535,
        "y": -5.262149,
        "z": 8.899458
      },
      "ambientLight": 59.2,
      "gyroscope": {
        "x": 0.6558598,
        "y": -1.3867862,
        "z": -0.11089822
      },
      "proximity": 5.0,
      "timestamp": 1763978755461
    },
    {
      "accelerometer": {
        "x": 6.148568,
        "y": -4.0255914,
        "z": 3.4044304
      },
      "ambientLight": 59.2,
      "gyroscope": {
        "x": 0.6558598,
        "y": -1.3867862,
        "z": -0.11089822
      },
      "proximity": 5.0,
      "timestamp": 1763978755561
    },
    {
      "accelerometer": {
        "x": 6.148568,
        "y": -4.0255914,
        "z": 3.4044304
      },
      "ambientLight": 59.2,
      "gyroscope": {
        "x": -1.0422409,
        "y": 0.72120494,
        "z": -0.5175948
      },
      "proximity": 5.0,
      "timestamp": 1763978755662
    },
    {
      "accelerometer": {
        "x": 8.226726,
        "y": -4.738853,
        "z": 7.333392
      },
      "ambientLight": 45.600002,
      "gyroscope": {
        "x": -1.0422409,
        "y": 0.72120494,
        "z": -0.5175948
      },
      "proximity": 5.0,
      "timestamp": 1763978755762
    },
    {
      "accelerometer": {
        "x": 8.226726,
        "y": -4.738853,
        "z": 7.333392
      },
      "ambientLight": 45.600002,
      "gyroscope": {
        "x": 0.98164296,
        "y": -0.44882888,
        "z": -0.33553955
      },
      "proximity": 5.0,
      "timestamp": 1763978755862
    },
    {
      "accelerometer": {
        "x": 8.661427,
        "y": -2.7785475,
        "z": 2.7726483
      },
      "ambientLight": 45.600002,
      "gyroscope": {
        "x": 0.91244066,
        "y": 0.052604225,
        "z": 0.493806
      },
      "proximity": 5.0,
      "timestamp": 1763978755989
    },
    {
      "accelerometer": {
        "x": 8.661427,
        "y": -2.7785475,
        "z": 2.7726483
      },
      "ambientLight": 60.0,
      "gyroscope": {
        "x": 0.91244066,
        "y": 0.052604225,
        "z": 0.493806
      },
      "proximity": 5.0,
      "timestamp": 1763978756090
    },
    {
      "accelerometer": {
        "x": 9.050149,
        "y": -4.0281005,
        "z": 4.430403
      },
      "ambientLight": 60.0,
      "gyroscope": {
        "x": -0.2022313,
        "y": 4.363323E-4,
        "z": -0.0012391837
      },
      "proximity": 5.0,
      "timestamp": 1763978756190
    },
    {
      "accelerometer": {
        "x": 9.050149,
        "y": -4.0281005,
        "z": 4.430403
      },
      "ambientLight": 60.0,
      "gyroscope": {
        "x": -0.2022313,
        "y": 4.363323E-4,
        "z": -0.0012391837
      },
      "proximity": 5.0,
      "timestamp": 1763978756290
    },
    {
      "accelerometer": {
        "x": 9.885476,
        "y": -1.7143346,
        "z": 3.1531637
      },
      "ambientLight": 64.700005,
      "gyroscope": {
        "x": -1.188098,
        "y": 0.8862258,
        "z": 0.026424285
      },
      "proximity": 5.0,
      "timestamp": 1763978756390
    },
    {
      "accelerometer": {
        "x": 9.885476,
        "y": -1.7143346,
        "z": 3.1531637
      },
      "ambientLight": 64.700005,
      "gyroscope": {
        "x": -1.188098,
        "y": 0.8862258,
        "z": 0.026424285
      },
      "proximity": 5.0,
      "timestamp": 1763978756490
    },
    {
      "accelerometer": {
        "x": 8.95826,
        "y": -3.4315805,
        "z": 6.8393817
      },
      "ambientLight": 64.700005,
      "gyroscope": {
        "x": 0.79426444,
        "y": -0.6883753,
        "z": -0.15561356
      },
      "proximity": 5.0,
      "timestamp": 1763978756590
    },
    {
      "accelerometer": {
        "x": 8.95826,
        "y": -3.4315805,
        "z": 6.8393817
      },
      "ambientLight": 64.700005,
      "gyroscope": {
        "x": 0.79426444,
        "y": -0.6883753,
        "z": -0.15561356
      },
      "proximity": 5.0,
      "timestamp": 1763978756691
    },
    {
      "accelerometer": {
        "x": 9.134004,
        "y": -3.1517081,
        "z": 0.8282405
      },
      "ambientLight": 54.4,
      "gyroscope": {
        "x": -1.3424723,
        "y": 1.1321602,
        "z": 0.24893631
      },
      "proximity": 5.0,
      "timestamp": 1763978756791
    },
    {
      "accelerometer": {
        "x": 9.134004,
        "y": -3.1517081,
        "z": 0.8282405
      },
      "ambientLight": 54.4,
      "gyroscope": {
        "x": -1.3424723,
        "y": 1.1321602,
        "z": 0.24893631
      },
      "proximity": 5.0,
      "timestamp": 1763978756891
    },
    {
      "accelerometer": {
        "x": 8.274859,
        "y": -3.9728713,
        "z": 3.9982786
      },
      "ambientLight": 54.4,
      "gyroscope": {
        "x": -0.4577475,
        "y": -0.47118655,
        "z": -0.044889867
      },
      "proximity": 5.0,
      "timestamp": 1763978756991
    },
    {
      "accelerometer": {
        "x": 8.333958,
        "y": -2.9509397,
        "z": 4.167261
      },
      "ambientLight": 47.7,
      "gyroscope": {
        "x": -0.4577475,
        "y": -0.47118655,
        "z": -0.044889867
      },
      "proximity": 5.0,
      "timestamp": 1763978757092
    },
    {
      "accelerometer": {
        "x": 8.333958,
        "y": -2.9509397,
        "z": 4.167261
      },
      "ambientLight": 47.7,
      "gyroscope": {
        "x": -0.057438787,
        "y": 1.593154,
        "z": 0.4352502
      },
      "proximity": 5.0,
      "timestamp": 1763978757192
    },
    {
      "accelerometer": {
        "x": 9.806861,
        "y": -2.4607701,
        "z": 5.3333907
      },
      "ambientLight": 47.7,
      "gyroscope": {
        "x": -0.057438787,
        "y": 1.593154,
        "z": 0.4352502
      },
      "proximity": 5.0,
      "timestamp": 1763978757293
    },
    {
      "accelerometer": {
        "x": 9.806861,
        "y": -2.4607701,
        "z": 5.3333907
      },
      "ambientLight": 47.7,
      "gyroscope": {
        "x": -0.60466933,
        "y": -0.12198106,
        "z": -0.3323456
      },
      "proximity": 5.0,
      "timestamp": 1763978757393
    },
    {
      "accelerometer": {
        "x": 11.089052,
        "y": -2.0038893,
        "z": 4.4015384
      },
      "ambientLight": 48.8,
      "gyroscope": {
        "x": -0.60466933,
        "y": -0.12198106,
        "z": -0.3323456
      },
      "proximity": 5.0,
      "timestamp": 1763978757493
    },
    {
      "accelerometer": {
        "x": 11.089052,
        "y": -2.0038893,
        "z": 4.4015384
      },
      "ambientLight": 48.8,
      "gyroscope": {
        "x": 0.8911477,
        "y": -0.27316147,
        "z": -0.2216219
      },
      "proximity": 5.0,
      "timestamp": 1763978757593
    },
    {
      "accelerometer": {
        "x": 8.272206,
        "y": -3.436953,
        "z": 3.7355962
      },
      "ambientLight": 48.8,
      "gyroscope": {
        "x": 0.8911477,
        "y": -0.27316147,
        "z": -0.2216219
      },
      "proximity": 5.0,
      "timestamp": 1763978757694
    },
    {
      "accelerometer": {
        "x": 8.272206,
        "y": -3.436953,
        "z": 3.7355962
      },
      "ambientLight": 62.600002,
      "gyroscope": {
        "x": -0.15325736,
        "y": 0.20697859,
        "z": -0.52185345
      },
      "proximity": 5.0,
      "timestamp": 1763978757794
    },
    {
      "accelerometer": {
        "x": 8.653076,
        "y": -1.6058868,
        "z": 3.967901
      },
      "ambientLight": 62.600002,
      "gyroscope": {
        "x": -0.15325736,
        "y": 0.20697859,
        "z": -0.52185345
      },
      "proximity": 5.0,
      "timestamp": 1763978757895
    },
    {
      "accelerometer": {
        "x": 8.653076,
        "y": -1.6058868,
        "z": 3.967901
      },
      "ambientLight": 62.600002,
      "gyroscope": {
        "x": 0.6388254,
        "y": -0.18586011,
        "z": 0.72909385
      },
      "proximity": 5.0,
      "timestamp": 1763978757995
    },
    {
      "accelerometer": {
        "x": 7.4217286,
        "y": -4.312436,
        "z": 4.1243668
      },
      "ambientLight": 62.600002,
      "gyroscope": {
        "x": 0.6388254,
        "y": -0.18586011,
        "z": 0.72909385
      },
      "proximity": 5.0,
      "timestamp": 1763978758096
    },
    {
      "accelerometer": {
        "x": 7.4217286,
        "y": -4.312436,
        "z": 4.1243668
      },
      "ambientLight": 62.3,
      "gyroscope": {
        "x": 0.19486602,
        "y": 0.019600047,
        "z": -0.30892327
      },
      "proximity": 5.0,
      "timestamp": 1763978758196
    },
    {
      "accelerometer": {
        "x": 9.576127,
        "y": -1.3631339,
        "z": 1.9555935
      },
      "ambientLight": 62.3,
      "gyroscope": {
        "x": 0.19486602,
        "y": 0.019600047,
        "z": -0.30892327
      },
      "proximity": 5.0,
      "timestamp": 1763978758297
    },
    {
      "accelerometer": {
        "x": 9.576127,
        "y": -1.3631339,
        "z": 1.9555935
      },
      "ambientLight": 62.3,
      "gyroscope": {
        "x": -1.124219,
        "y": 0.6466794,
        "z": 0.015777776
      },
      "proximity": 5.0,
      "timestamp": 1763978758397
    },
    {
      "accelerometer": {
        "x": 8.274839,
        "y": -3.8180718,
        "z": 3.690432
      },
      "ambientLight": 54.9,
      "gyroscope": {
        "x": -1.124219,
        "y": 0.6466794,
        "z": 0.015777776
      },
      "proximity": 5.0,
      "timestamp": 1763978758498
    },
    {
      "accelerometer": {
        "x": 8.274839,
        "y": -3.8180718,
        "z": 3.690432
      },
      "ambientLight": 54.9,
      "gyroscope": {
        "x": -0.36086428,
        "y": 0.36454692,
        "z": -0.5005604
      },
      "proximity": 5.0,
      "timestamp": 1763978758598
    },
    {
      "accelerometer": {
        "x": 8.120854,
        "y": -2.7967532,
        "z": 3.931423
      },
      "ambientLight": 54.9,
      "gyroscope": {
        "x": -0.36086428,
        "y": 0.36454692,
        "z": -0.5005604
      },
      "proximity": 5.0,
      "timestamp": 1763978758698
    },
    {
      "accelerometer": {
        "x": 8.120854,
        "y": -2.7967532,
        "z": 3.931423
      },
      "ambientLight": 54.9,
      "gyroscope": {
        "x": -0.14899875,
        "y": -0.091106184,
        "z": -0.17584193
      },
      "proximity": 5.0,
      "timestamp": 1763978758798
    },
    {
      "accelerometer": {
        "x": 8.120854,
        "y": -2.7967532,
        "z": 3.931423
      },
      "ambientLight": 54.9,
      "gyroscope": {
        "x": -0.14899875,
        "y": -0.091106184,
        "z": -0.17584193
      },
      "proximity": 5.0,
      "timestamp": 1763978758898
    }
  ],
  "type": "other"
}