{
  "duration": 8,
  "sensors": [
    {
      "accelerometer": {
        "x": -1.1550001,
        "y": 4.6810503,
        "z": 8.398951
      },
      "ambientLight": 10.869565,
      "gyroscope": {
        "x": -0.0122375,
        "y": 0.0435875,
        "z": 0.01925
      },
      "proximity": 5.0,
      "timestamp": 1763962464814
    },
    {
      "accelerometer": {
        "x": -1.1689501,
        "y": 4.75995,
        "z": 8.554951
      },
      "ambientLight": 11.645963,
      "gyroscope": {
        "x": -0.091299996,
        "y": -0.0086624995,
        "z": -0.034649998
      },
      "proximity": 5.0,
      "timestamp": 1763962465027
    },
    {
      "accelerometer": {
        "x": -1.03695,
        "y": 4.5490503,
        "z": 8.46195
      },
      "ambientLight": 10.869565,
      "gyroscope": {
        "x": -0.041249998,
        "y": 0.1012,
        "z": 0.001375
      },
      "proximity": 5.0,
      "timestamp": 1763962465169
    },
    {
      "accelerometer": {
        "x": -1.08,
        "y": 4.72905,
        "z": 8.32995
      },
      "ambientLight": 10.869565,
      "gyroscope": {
        "x": 0.06875,
        "y": -0.1654125,
        "z": 0.095699996
      },
      "proximity": 5.0,
      "timestamp": 1763962465276
    },
    {
      "accelerometer": {
        "x": -0.33600003,
        "y": 4.47795,
        "z": 8.481
      },
      "ambientLight": 10.869565,
      "gyroscope": {
        "x": -0.2239875,
        "y": -0.22013749,
        "z": 0.044275
      },
      "proximity": 5.0,
      "timestamp": 1763962465376
    },
    {
      "accelerometer": {
        "x": -0.18195,
        "y": 4.4419503,
        "z": 8.101951
      },
      "ambientLight": 11.645963,
      "gyroscope": {
        "x": 0.011825,
        "y": -0.47808748,
        "z": 0.07095
      },
      "proximity": 5.0,
      "timestamp": 1763962465477
    },
    {
      "accelerometer": {
        "x": -0.38805002,
        "y": 5.74695,
        "z": 7.2450004
      },
      "ambientLight": 11.645963,
      "gyroscope": {
        "x": 0.7569375,
        "y": -0.33165,
        "z": 0.0702625
      },
      "proximity": 5.0,
      "timestamp": 1763962465578
    },
    {
      "accelerometer": {
        "x": -0.87405,
        "y": 5.48295,
        "z": 6.13395
      },
      "ambientLight": 10.869565,
      "gyroscope": {
        "x": 0.4453625,
        "y": 0.7349375,
        "z": -0.287925
      },
      "proximity": 5.0,
      "timestamp": 1763962465679
    },
    {
      "accelerometer": {
        "x": -1.9540501,
        "y": 4.92105,
        "z": 5.4040504
      },
      "ambientLight": 10.093168,
      "gyroscope": {
        "x": 0.0295625,
        "y": 1.758075,
        "z": -0.6975375
      },
      "proximity": 5.0,
      "timestamp": 1763962465780
    },
    {
      "accelerometer": {
        "x": -2.775,
        "y": 5.92395,
        "z": 6.6610503
      },
      "ambientLight": 10.093168,
      "gyroscope": {
        "x": 1.646425,
        "y": 0.7858125,
        "z": 0.0053625
      },
      "proximity": 5.0,
      "timestamp": 1763962465885
    },
    {
      "accelerometer": {
        "x": -3.561,
        "y": 5.27505,
        "z": 4.02705
      },
      "ambientLight": 9.316771,
      "gyroscope": {
        "x": 1.1779625,
        "y": 1.3099625,
        "z": -0.87285
      },
      "proximity": 5.0,
      "timestamp": 1763962465986
    },
    {
      "accelerometer": {
        "x": -2.6580002,
        "y": 2.505,
        "z": 1.0009501
      },
      "ambientLight": 8.540373,
      "gyroscope": {
        "x": 1.2914,
        "y": 1.993475,
        "z": -1.3294874
      },
      "proximity": 5.0,
      "timestamp": 1763962466087
    },
    {
      "accelerometer": {
        "x": -2.8330503,
        "y": 4.308,
        "z": 4.43205
      },
      "ambientLight": 8.540373,
      "gyroscope": {
        "x": 4.8283124,
        "y": 3.083575,
        "z": 2.9041374
      },
      "proximity": 5.0,
      "timestamp": 1763962466188
    },
    {
      "accelerometer": {
        "x": 7.6050005,
        "y": 0.81705004,
        "z": -11.307
      },
      "ambientLight": 6.21118,
      "gyroscope": {
        "x": 4.0723376,
        "y": 3.394875,
        "z": 0.996325
      },
      "proximity": 5.0,
      "timestamp": 1763962466289
    },
    {
      "accelerometer": {
        "x": -28.513952,
        "y": 13.954051,
        "z": -13.504951
      },
      "ambientLight": 2.3291926,
      "gyroscope": {
        "x": -11.839025,
        "y": 0.7414,
        "z": 2.8004625
      },
      "proximity": 5.0,
      "timestamp": 1763962466390
    },
    {
      "accelerometer": {
        "x": -12.135,
        "y": -6.846,
        "z": 1.60905
      },
      "ambientLight": 2.3291926,
      "gyroscope": {
        "x": 2.028675,
        "y": -0.091299996,
        "z": -7.5926123
      },
      "proximity": 5.0,
      "timestamp": 1763962466491
    },
    {
      "accelerometer": {
        "x": -1.8270001,
        "y": -7.1119504,
        "z": -7.51695
      },
      "ambientLight": 3.10559,
      "gyroscope": {
        "x": 6.9906373,
        "y": 10.4901495,
        "z": -3.3532126
      },
      "proximity": 0.0,
      "timestamp": 1763962466592
    },
    {
      "accelerometer": {
        "x": 3.24495,
        "y": -4.2720003,
        "z": -18.157051
      },
      "ambientLight": 6.21118,
      "gyroscope": {
        "x": 2.6085124,
        "y": 0.9362375,
        "z": 0.7596875
      },
      "proximity": 0.0,
      "timestamp": 1763962466693
    },
    {
      "accelerometer": {
        "x": 2.5510502,
        "y": 3.4410002,
        "z": -1.77495
      },
      "ambientLight": 6.21118,
      "gyroscope": {
        "x": -2.4519,
        "y": 4.236925,
        "z": 2.3307624
      },
      "proximity": 0.0,
      "timestamp": 1763962466794
    },
    {
      "accelerometer": {
        "x": -0.51000005,
        "y": 2.5069501,
        "z": -12.576
      },
      "ambientLight": 9.316771,
      "gyroscope": {
        "x": -9.023163,
        "y": -4.05955,
        "z": 0.988075
      },
      "proximity": 0.0,
      "timestamp": 1763962466895
    },
    {
      "accelerometer": {
        "x": -2.9479501,
        "y": 2.2459502,
        "z": -10.40205
      },
      "ambientLight": 8.540373,
      "gyroscope": {
        "x": -0.2033625,
        "y": -0.1282875,
        "z": 0.087175
      },
      "proximity": 0.0,
      "timestamp": 1763962466995
    },
    {
      "accelerometer": {
        "x": -1.8610501,
        "y": 3.73305,
        "z": -9.777
      },
      "ambientLight": 8.540373,
      "gyroscope": {
        "x": 1.0373,
        "y": 0.9400875,
        "z": 0.7194
      },
      "proximity": 0.0,
      "timestamp": 1763962467095
    },
    {
      "accelerometer": {
        "x": -2.67705,
        "y": 5.0950503,
        "z": -8.785951
      },
      "ambientLight": 7.763975,
      "gyroscope": {
        "x": -1.1757625,
        "y": -0.1604625,
        "z": 0.519475
      },
      "proximity": 0.0,
      "timestamp": 1763962467196
    },
    {
      "accelerometer": {
        "x": -2.00895,
        "y": 3.1320002,
        "z": -9.14505
      },
      "ambientLight": 6.987578,
      "gyroscope": {
        "x": 0.56045,
        "y": 0.2481875,
        "z": -0.1458875
      },
      "proximity": 0.0,
      "timestamp": 1763962467296
    },
    {
      "accelerometer": {
        "x": -1.7890501,
        "y": 3.2299502,
        "z": -9.18795
      },
      "ambientLight": 6.987578,
      "gyroscope": {
        "x": 0.2256375,
        "y": -0.0669625,
        "z": -0.1439625
      },
      "proximity": 0.0,
      "timestamp": 1763962467396
    },
    {
      "accelerometer": {
        "x": -1.5640501,
        "y": 3.4069502,
        "z": -9.078
      },
      "ambientLight": 6.987578,
      "gyroscope": {
        "x": -0.146025,
        "y": 0.0757625,
        "z": 0.1106875
      },
      "proximity": 0.0,
      "timestamp": 1763962467497
    },
    {
      "accelerometer": {
        "x": -1.6860001,
        "y": 3.39105,
        "z": -9.00405
      },
      "ambientLight": 6.987578,
      "gyroscope": {
        "x": 0.052525,
        "y": 0.0011,
        "z": -0.0044
      },
      "proximity": 0.0,
      "timestamp": 1763962467598
    },
    {
      "accelerometer": {
        "x": -1.794,
        "y": 3.41895,
        "z": -9.159
      },
      "ambientLight": 6.987578,
      "gyroscope": {
        "x": 0.01155,
        "y": -0.007425,
        "z": -0.012375
      },
      "proximity": 0.0,
      "timestamp": 1763962467699
    },
    {
      "accelerometer": {
        "x": -1.7320501,
        "y": 3.42405,
        "z": -9.11205
      },
      "ambientLight": 6.987578,
      "gyroscope": {
        "x": -0.0022,
        "y": -5.5E-4,
        "z": -0.0045375
      },
      "proximity": 0.0,
      "timestamp": 1763962467799
    },
    {
      "accelerometer": {
        "x": -1.7359501,
        "y": 3.3930001,
        "z": -9.14505
      },
      "ambientLight": 6.987578,
      "gyroscope": {
        "x": 0.00165,
        "y": 0.0031625,
        "z": -0.003575
      },
      "proximity": 0.0,
      "timestamp": 1763962467965
    },
    {
      "accelerometer": {
        "x": -1.6840501,
        "y": 3.3760502,
        "z": -9.147
      },
      "ambientLight": 6.987578,
      "gyroscope": {
        "x": -0.0020625,
        "y": 0.004125,
        "z": 0.004675
      },
      "proximity": 0.0,
      "timestamp": 1763962468066
    },
    {
      "accelerometer": {
        "x": -1.6980001,
        "y": 3.4000502,
        "z": -9.127951
      },
      "ambientLight": 6.987578,
      "gyroscope": {
        "x": -4.125E-4,
        "y": -0.0044,
        "z": 0.0042625
      },
      "proximity": 0.0,
      "timestamp": 1763962468166
    },
    {
      "accelerometer": {
        "x": -1.7170501,
        "y": 3.38595,
        "z": -9.118951
      },
      "ambientLight": 6.987578,
      "gyroscope": {
        "x": -6.875E-4,
        "y": -0.002475,
        "z": -0.0020625
      },
      "proximity": 0.0,
      "timestamp": 1763962468266
    },
    {
      "accelerometer": {
        "x": -1.7119501,
        "y": 3.39105,
        "z": -9.09195
      },
      "ambientLight": 6.987578,
      "gyroscope": {
        "x": 0.00275,
        "y": 0.00165,
        "z": 0.0017875
      },
      "proximity": 0.0,
      "timestamp": 1763962468368
    },
    {
      "accelerometer": {
        "x": -1.746,
        "y": 3.3949502,
        "z": -9.17895
      },
      "ambientLight": 6.987578,
      "gyroscope": {
        "x": -0.003575,
        "y": -6.875E-4,
        "z": -8.25E-4
      },
      "proximity": 0.0,
      "timestamp": 1763962468470
    },
    {
      "accelerometer": {
        "x": -1.74405,
        "y": 3.4050002,
        "z": -9.115951
      },
      "ambientLight": 6.987578,
      "gyroscope": {
        "x": -0.0015125,
        "y": -1.375E-4,
        "z": 0.0017875
      },
      "proximity": 0.0,
      "timestamp": 1763962468573
    },
    {
      "accelerometer": {
        "x": -1.6999501,
        "y": 3.4030502,
        "z": -9.14295
      },
      "ambientLight": 6.987578,
      "gyroscope": {
        "x": -0.00385,
        "y": 0.0048125,
        "z": -0.003025
      },
      "proximity": 0.0,
      "timestamp": 1763962468674
    },
    {
      "accelerometer": {
        "x": -1.7170501,
        "y": 3.348,
        "z": -9.09
      },
      "ambientLight": 6.987578,
      "gyroscope": {
        "x": -0.00495,
        "y": -0.0017875,
        "z": 0.002475
      },
      "proximity": 0.0,
      "timestamp": 1763962468774
    },
    {
      "accelerometer": {
        "x": -1.69605,
        "y": 3.3709502,
        "z": -9.16395
      },
      "ambientLight": 6.987578,
      "gyroscope": {
        "x": -2.75E-4,
        "y": -0.0011,
        "z": 0.0034375
      },
      "proximity": 0.0,
      "timestamp": 1763962468946
    },
    {
      "accelerometer": {
        "x": -1.6980001,
        "y": 3.4099503,
        "z": -9.15495
      },
      "ambientLight": 6.987578,
      "gyroscope": {
        "x": -0.0039875,
        "y": 0.004675,
        "z": -0.001925
      },
      "proximity": 0.0,
      "timestamp": 1763962469047
    },
    {
      "accelerometer": {
        "x": -1.69305,
        "y": 3.4120502,
        "z": -9.02505
      },
      "ambientLight": 6.987578,
      "gyroscope": {
        "x": 0.0026125,
        "y": 0.0022,
        "z": -0.0017875
      },
      "proximity": 0.0,
      "timestamp": 1763962469147
    },
    {
      "accelerometer": {
        "x": -1.69605,
        "y": 3.3979502,
        "z": -9.13095
      },
      "ambientLight": 6.987578,
      "gyroscope": {
        "x": 5.5E-4,
        "y": 0.0026125,
        "z": 0.0
      },
      "proximity": 0.0,
      "timestamp": 1763962469248
    },
    {
      "accelerometer": {
        "x": -1.7080501,
        "y": 3.4099503,
        "z": -9.14505
      },
      "ambientLight": 6.987578,
      "gyroscope": {
        "x": 0.0020625,
        "y": -2.75E-4,
        "z": -0.0034375
      },
      "proximity": 0.0,
      "timestamp": 1763962469348
    },
    {
      "accelerometer": {
        "x": -1.7149501,
        "y": 3.4290001,
        "z": -9.076051
      },
      "ambientLight": 6.987578,
      "gyroscope": {
        "x": -4.125E-4,
        "y": 4.125E-4,
        "z": -0.0031625
      },
      "proximity": 0.0,
      "timestamp": 1763962469450
    },
    {
      "accelerometer": {
        "x": -1.66005,
        "y": 3.4290001,
        "z": -9.09
      },
      "ambientLight": 6.987578,
      "gyroscope": {
        "x": -0.004675,
        "y": -0.0022,
        "z": 2.75E-4
      },
      "proximity": 0.0,
      "timestamp": 1763962469550
    },
    {
      "accelerometer": {
        "x": -1.69605,
        "y": 3.4069502,
        "z": -9.109051
      },
      "ambientLight": 6.987578,
      "gyroscope": {
        "x": -0.0033,
        "y": 0.0042625,
        "z": -0.00275
      },
      "proximity": 0.0,
      "timestamp": 1763962469650
    },
    {
      "accelerometer": {
        "x": -1.7389501,
        "y": 3.41895,
        "z": -9.159
      },
      "ambientLight": 6.987578,
      "gyroscope": {
        "x": 0.001925,
        "y": -0.002475,
        "z": -0.0015125
      },
      "proximity": 0.0,
      "timestamp": 1763962469751
    },
    {
      "accelerometer": {
        "x": -1.6860001,
        "y": 3.42705,
        "z": -9.09195
      },
      "ambientLight": 6.987578,
      "gyroscope": {
        "x": -0.0015125,
        "y": 0.004675,
        "z": -0.0020625
      },
      "proximity": 0.0,
      "timestamp": 1763962469954
    },
    {
      "accelerometer": {
        "x": -1.6860001,
        "y": 3.39105,
        "z": -9.109051
      },
      "ambientLight": 6.987578,
      "gyroscope": {
        "x": -0.00385,
        "y": 0.0011,
        "z": -0.002475
      },
      "proximity": 0.0,
      "timestamp": 1763962470054
    },
    {
      "accelerometer": {
        "x": -1.72695,
        "y": 3.41895,
        "z": -9.1380005
      },
      "ambientLight": 6.987578,
      "gyroscope": {
        "x": 2.75E-4,
        "y": 2.75E-4,
        "z": -0.0020625
      },
      "proximity": 0.0,
      "timestamp": 1763962470155
    },
    {
      "accelerometer": {
        "x": -1.7149501,
        "y": 3.42195,
        "z": -9.12405
      },
      "ambientLight": 6.987578,
      "gyroscope": {
        "x": 6.875E-4,
        "y": 0.0033,
        "z": 0.0023375
      },
      "proximity": 0.0,
      "timestamp": 1763962470256
    },
    {
      "accelerometer": {
        "x": -1.72695,
        "y": 3.42705,
        "z": -9.15495
      },
      "ambientLight": 6.987578,
      "gyroscope": {
        "x": 0.00275,
        "y": 0.0011,
        "z": -0.0012375
      },
      "proximity": 0.0,
      "timestamp": 1763962470356
    },
    {
      "accelerometer": {
        "x": -1.7320501,
        "y": 3.4150503,
        "z": -9.14505
      },
      "ambientLight": 6.21118,
      "gyroscope": {
        "x": 0.00275,
        "y": 0.00495,
        "z": 0.003575
      },
      "proximity": 0.0,
      "timestamp": 1763962470457
    },
    {
      "accelerometer": {
        "x": -1.6860001,
        "y": 3.4000502,
        "z": -9.115951
      },
      "ambientLight": 6.21118,
      "gyroscope": {
        "x": 0.00495,
        "y": -0.0012375,
        "z": -0.0012375
      },
      "proximity": 0.0,
      "timestamp": 1763962470557
    },
    {
      "accelerometer": {
        "x": -1.7050501,
        "y": 3.4050002,
        "z": -9.127951
      },
      "ambientLight": 6.987578,
      "gyroscope": {
        "x": 4.125E-4,
        "y": -0.004125,
        "z": -0.0048125
      },
      "proximity": 0.0,
      "timestamp": 1763962470658
    },
    {
      "accelerometer": {
        "x": -1.6999501,
        "y": 3.38295,
        "z": -9.14505
      },
      "ambientLight": 6.987578,
      "gyroscope": {
        "x": 0.0044,
        "y": 0.0031625,
        "z": -8.25E-4
      },
      "proximity": 0.0,
      "timestamp": 1763962470758
    },
    {
      "accelerometer": {
        "x": -1.6669501,
        "y": 3.41895,
        "z": -9.15705
      },
      "ambientLight": 6.987578,
      "gyroscope": {
        "x": 0.0037125,
        "y": -0.0045375,
        "z": -1.375E-4
      },
      "proximity": 0.0,
      "timestamp": 1763962470957
    },
    {
      "accelerometer": {
        "x": -1.6840501,
        "y": 3.42405,
        "z": -9.14505
      },
      "ambientLight": 6.987578,
      "gyroscope": {
        "x": 6.875E-4,
        "y": 0.001925,
        "z": 0.001375
      },
      "proximity": 0.0,
      "timestamp": 1763962471057
    },
    {
      "accelerometer": {
        "x": -1.6720501,
        "y": 3.4309502,
        "z": -9.126
      },
      "ambientLight": 6.987578,
      "gyroscope": {
        "x": -0.0017875,
        "y": 9.625E-4,
        "z": -0.00165
      },
      "proximity": 0.0,
      "timestamp": 1763962471158
    },
    {
      "accelerometer": {
        "x": -1.7080501,
        "y": 3.4050002,
        "z": -9.151951
      },
      "ambientLight": 6.987578,
      "gyroscope": {
        "x": -0.004675,
        "y": 0.0028875,
        "z": -0.0034375
      },
      "proximity": 0.0,
      "timestamp": 1763962471258
    },
    {
      "accelerometer": {
        "x": -1.72395,
        "y": 3.45795,
        "z": -9.114
      },
      "ambientLight": 6.987578,
      "gyroscope": {
        "x": 0.0015125,
        "y": 0.0034375,
        "z": -0.0015125
      },
      "proximity": 0.0,
      "timestamp": 1763962471361
    },
    {
      "accelerometer": {
        "x": -1.69305,
        "y": 3.41895,
        "z": -9.139951
      },
      "ambientLight": 6.987578,
      "gyroscope": {
        "x": 0.0048125,
        "y": 0.00495,
        "z": -0.001375
      },
      "proximity": 0.0,
      "timestamp": 1763962471462
    },
    {
      "accelerometer": {
        "x": -1.6789501,
        "y": 3.42405,
        "z": -9.147
      },
      "ambientLight": 6.987578,
      "gyroscope": {
        "x": -0.0015125,
        "y": 0.0015125,
        "z": -0.0042625
      },
      "proximity": 0.0,
      "timestamp": 1763962471562
    },
    {
      "accelerometer": {
        "x": -1.7080501,
        "y": 3.4429502,
        "z": -9.115951
      },
      "ambientLight": 6.987578,
      "gyroscope": {
        "x": -0.0026125,
        "y": 0.0022,
        "z": -0.00275
      },
      "proximity": 0.0,
      "timestamp": 1763962471664
    },
    {
      "accelerometer": {
        "x": -1.6980001,
        "y": 3.4360502,
        "z": -9.097051
      },
      "ambientLight": 6.987578,
      "gyroscope": {
        "x": -0.001925,
        "y": -0.0033,
        "z": -0.0028875
      },
      "proximity": 0.0,
      "timestamp": 1763962471764
    },
    {
      "accelerometer": {
        "x": -1.7050501,
        "y": 3.4120502,
        "z": -9.115951
      },
      "ambientLight": 6.987578,
      "gyroscope": {
        "x": -0.0012375,
        "y": -0.00275,
        "z": 5.5E-4
      },
      "proximity": 0.0,
      "timestamp": 1763962471950
    },
    {
      "accelerometer": {
        "x": -1.6999501,
        "y": 3.4309502,
        "z": -9.13305
      },
      "ambientLight": 6.987578,
      "gyroscope": {
        "x": -0.003025,
        "y": 0.004675,
        "z": 0.004125
      },
      "proximity": 0.0,
      "timestamp": 1763962472051
    },
    {
      "accelerometer": {
        "x": -1.72395,
        "y": 3.4339502,
        "z": -9.14295
      },
      "ambientLight": 6.987578,
      "gyroscope": {
        "x": -5.5E-4,
        "y": 0.0042625,
        "z": -0.0042625
      },
      "proximity": 0.0,
      "timestamp": 1763962472154
    },
    {
      "accelerometer": {
        "x": -1.7340001,
        "y": 3.41895,
        "z": -9.1380005
      },
      "ambientLight": 6.987578,
      "gyroscope": {
        "x": -0.00385,
        "y": -6.875E-4,
        "z": -2.75E-4
      },
      "proximity": 0.0,
      "timestamp": 1763962472255
    },
    {
      "accelerometer": {
        "x": -1.7149501,
        "y": 3.42195,
        "z": -9.13305
      },
      "ambientLight": 6.987578,
      "gyroscope": {
        "x": -0.004125,
        "y": 0.0017875,
        "z": -0.0022
      },
      "proximity": 0.0,
      "timestamp": 1763962472355
    },
    {
      "accelerometer": {
        "x": -1.7080501,
        "y": 3.4099503,
        "z": -9.147
      },
      "ambientLight": 6.987578,
      "gyroscope": {
        "x": 0.004675,
        "y": 0.00495,
        "z": -0.0017875
      },
      "proximity": 0.0,
      "timestamp": 1763962472456
    },
    {
      "accelerometer": {
        "x": -1.67595,
        "y": 3.4390502,
        "z": -9.115951
      },
      "ambientLight": 6.987578,
      "gyroscope": {
        "x": -0.0028875,
        "y": 0.0031625,
        "z": -0.0022
      },
      "proximity": 0.0,
      "timestamp": 1763962472557
    },
    {
      "accelerometer": {
        "x": -1.69605,
        "y": 3.4000502,
        "z": -9.147
      },
      "ambientLight": 6.987578,
      "gyroscope": {
        "x": 0.003025,
        "y": 0.0012375,
        "z": 0.0017875
      },
      "proximity": 0.0,
      "timestamp": 1763962472659
    },
    {
      "accelerometer": {
        "x": -1.6980001,
        "y": 3.4120502,
        "z": -9.14295
      },
      "ambientLight": 6.987578,
      "gyroscope": {
        "x": 0.0033,
        "y": -4.125E-4,
        "z": -0.003575
      },
      "proximity": 0.0,
      "timestamp": 1763962472759
    }
  ],
  "type": "fall"
}